{
   "agent": "Boost.Beast/164-Sync",
   "behavior": "OK",
   "behaviorClose": "OK",
   "case": 303,
   "closedByMe": true,
   "createStats": true,
   "createWirelog": true,
   "description": "Send text message with payload of length 65536 auto-fragmented with <b>autoFragmentSize = 1300</b>.",
   "droppedByMe": false,
   "duration": 2,
   "expectation": "Receive echo'ed text message (with payload as sent and transmitted frame counts as expected). Clean close with normal code.",
   "expected": {
      "OK": [
         [
            "message",
            "**************************************************************** ...",
            false
         ]
      ]
   },
   "expectedClose": {
      "closeCode": [
         1000
      ],
      "closedByMe": true,
      "requireClean": true
   },
   "failedByMe": false,
   "httpRequest": "GET / HTTP/1.1\r\nUser-Agent: AutobahnTestSuite/0.7.6-0.10.9\r\nHost: 127.0.0.1:8080\r\nUpgrade: WebSocket\r\nConnection: Upgrade\r\nPragma: no-cache\r\nCache-Control: no-cache\r\nSec-WebSocket-Key: +vBIrqKlnnebNIMoVuJb1A==\r\nSec-WebSocket-Version: 13\r\n\r\n",
   "httpResponse": "HTTP/1.1 101 Switching Protocols\r\nUpgrade: websocket\r\nConnection: upgrade\r\nSec-WebSocket-Accept: lZ1pFhe7xmQmc3tHcXNauUTtmr8=\r\nServer: Boost.Beast/164-Sync\r\n\r\n",
   "id": "10.1.1",
   "isServer": false,
   "localCloseCode": 1000,
   "localCloseReason": null,
   "received": [
      [
         "message",
         "**************************************************************** ...",
         false
      ]
   ],
   "remoteCloseCode": 1000,
   "remoteCloseReason": null,
   "reportCompressionRatio": false,
   "reportTime": false,
   "result": "Actual events match at least one expected.",
   "resultClose": "Connection was properly closed",
   "rxFrameStats": {
      "1": 1,
      "8": 1
   },
   "rxOctetStats": {
      "4": 1,
      "159": 1,
      "24666": 1,
      "40880": 1
   },
   "started": "2018-03-11T17:14:57.738Z",
   "trafficStats": null,
   "txFrameStats": {
      "0": 50,
      "1": 1,
      "8": 1
   },
   "txOctetStats": {
      "8": 1,
      "240": 1,
      "544": 1,
      "1308": 50
   },
   "wasClean": true,
   "wasCloseHandshakeTimeout": false,
   "wasNotCleanReason": null,
   "wasOpenHandshakeTimeout": false,
   "wasServerConnectionDropTimeout": false,
   "wirelog": [
      [
         "TO",
         [
            240,
            "474554202f20485454502f312e310d0a557365722d4167656e743a204175746f6261686e5465737453756974652f302e372e362d302e31302e390d0a486f7374 ..."
         ],
         false
      ],
      [
         "RO",
         [
            159,
            "485454502f312e312031303120537769746368696e672050726f746f636f6c730d0a557067726164653a20776562736f636b65740d0a436f6e6e656374696f6e ..."
         ]
      ],
      [
         "TF",
         [
            1300,
            "**************************************************************** ..."
         ],
         1,
         false,
         0,
         "39c289bb",
         null,
         null,
         false
      ],
      [
         "TO",
         [
            1308,
            "01fe051439c289bb13e8a39113e8a39113e8a39113e8a39113e8a39113e8a39113e8a39113e8a39113e8a39113e8a39113e8a39113e8a39113e8a39113e8a391 ..."
         ],
         false
      ],
      [
         "TF",
         [
            1300,
            "**************************************************************** ..."
         ],
         0,
         false,
         0,
         "b17c868a",
         null,
         null,
         false
      ],
      [
         "TO",
         [
            1308,
            "00fe0514b17c868a9b56aca09b56aca09b56aca09b56aca09b56aca09b56aca09b56aca09b56aca09b56aca09b56aca09b56aca09b56aca09b56aca09b56aca0 ..."
         ],
         false
      ],
      [
         "TF",
         [
            1300,
            "**************************************************************** ..."
         ],
         0,
         false,
         0,
         "24b78df6",
         null,
         null,
         false
      ],
      [
         "TO",
         [
            1308,
            "00fe051424b78df60e9da7dc0e9da7dc0e9da7dc0e9da7dc0e9da7dc0e9da7dc0e9da7dc0e9da7dc0e9da7dc0e9da7dc0e9da7dc0e9da7dc0e9da7dc0e9da7dc ..."
         ],
         false
      ],
      [
         "TF",
         [
            1300,
            "**************************************************************** ..."
         ],
         0,
         false,
         0,
         "ed3c0754",
         null,
         null,
         false
      ],
      [
         "TO",
         [
            1308,
            "00fe0514ed3c0754c7162d7ec7162d7ec7162d7ec7162d7ec7162d7ec7162d7ec7162d7ec7162d7ec7162d7ec7162d7ec7162d7ec7162d7ec7162d7ec7162d7e ..."
         ],
         false
      ],
      [
         "TF",
         [
            1300,
            "**************************************************************** ..."
         ],
         0,
         false,
         0,
         "4c79b15b",
         null,
         null,
         false
      ],
      [
         "TO",
         [
            1308,
            "00fe05144c79b15b66539b7166539b7166539b7166539b7166539b7166539b7166539b7166539b7166539b7166539b7166539b7166539b7166539b7166539b71 ..."
         ],
         false
      ],
      [
         "TF",
         [
            1300,
            "**************************************************************** ..."
         ],
         0,
         false,
         0,
         "2477ee01",
         null,
         null,
         false
      ],
      [
         "TO",
         [
            1308,
            "00fe05142477ee010e5dc42b0e5dc42b0e5dc42b0e5dc42b0e5dc42b0e5dc42b0e5dc42b0e5dc42b0e5dc42b0e5dc42b0e5dc42b0e5dc42b0e5dc42b0e5dc42b ..."
         ],
         false
      ],
      [
         "TF",
         [
            1300,
            "**************************************************************** ..."
         ],
         0,
         false,
         0,
         "39eccd77",
         null,
         null,
         false
      ],
      [
         "TO",
         [
            1308,
            "00fe051439eccd7713c6e75d13c6e75d13c6e75d13c6e75d13c6e75d13c6e75d13c6e75d13c6e75d13c6e75d13c6e75d13c6e75d13c6e75d13c6e75d13c6e75d ..."
         ],
         false
      ],
      [
         "TF",
         [
            1300,
            "**************************************************************** ..."
         ],
         0,
         false,
         0,
         "5aa31905",
         null,
         null,
         false
      ],
      [
         "TO",
         [
            1308,
            "00fe05145aa319057089332f7089332f7089332f7089332f7089332f7089332f7089332f7089332f7089332f7089332f7089332f7089332f7089332f7089332f ..."
         ],
         false
      ],
      [
         "TF",
         [
            1300,
            "**************************************************************** ..."
         ],
         0,
         false,
         0,
         "5a7334dd",
         null,
         null,
         false
      ],
      [
         "TO",
         [
            1308,
            "00fe05145a7334dd70591ef770591ef770591ef770591ef770591ef770591ef770591ef770591ef770591ef770591ef770591ef770591ef770591ef770591ef7 ..."
         ],
         false
      ],
      [
         "TF",
         [
            1300,
            "**************************************************************** ..."
         ],
         0,
         false,
         0,
         "32c6ee8a",
         null,
         null,
         false
      ],
      [
         "TO",
         [
            1308,
            "00fe051432c6ee8a18ecc4a018ecc4a018ecc4a018ecc4a018ecc4a018ecc4a018ecc4a018ecc4a018ecc4a018ecc4a018ecc4a018ecc4a018ecc4a018ecc4a0 ..."
         ],
         false
      ],
      [
         "TF",
         [
            1300,
            "**************************************************************** ..."
         ],
         0,
         false,
         0,
         "877a77c2",
         null,
         null,
         false
      ],
      [
         "TO",
         [
            1308,
            "00fe0514877a77c2ad505de8ad505de8ad505de8ad505de8ad505de8ad505de8ad505de8ad505de8ad505de8ad505de8ad505de8ad505de8ad505de8ad505de8 ..."
         ],
         false
      ],
      [
         "TF",
         [
            1300,
            "**************************************************************** ..."
         ],
         0,
         false,
         0,
         "c04ce4aa",
         null,
         null,
         false
      ],
      [
         "TO",
         [
            1308,
            "00fe0514c04ce4aaea66ce80ea66ce80ea66ce80ea66ce80ea66ce80ea66ce80ea66ce80ea66ce80ea66ce80ea66ce80ea66ce80ea66ce80ea66ce80ea66ce80 ..."
         ],
         false
      ],
      [
         "TF",
         [
            1300,
            "**************************************************************** ..."
         ],
         0,
         false,
         0,
         "a0127d01",
         null,
         null,
         false
      ],
      [
         "TO",
         [
            1308,
            "00fe0514a0127d018a38572b8a38572b8a38572b8a38572b8a38572b8a38572b8a38572b8a38572b8a38572b8a38572b8a38572b8a38572b8a38572b8a38572b ..."
         ],
         false
      ],
      [
         "TF",
         [
            1300,
            "**************************************************************** ..."
         ],
         0,
         false,
         0,
         "112a5750",
         null,
         null,
         false
      ],
      [
         "TO",
         [
            1308,
            "00fe0514112a57503b007d7a3b007d7a3b007d7a3b007d7a3b007d7a3b007d7a3b007d7a3b007d7a3b007d7a3b007d7a3b007d7a3b007d7a3b007d7a3b007d7a ..."
         ],
         false
      ],
      [
         "TF",
         [
            1300,
            "**************************************************************** ..."
         ],
         0,
         false,
         0,
         "d592b1d0",
         null,
         null,
         false
      ],
      [
         "TO",
         [
            1308,
            "00fe0514d592b1d0ffb89bfaffb89bfaffb89bfaffb89bfaffb89bfaffb89bfaffb89bfaffb89bfaffb89bfaffb89bfaffb89bfaffb89bfaffb89bfaffb89bfa ..."
         ],
         false
      ],
      [
         "TF",
         [
            1300,
            "**************************************************************** ..."
         ],
         0,
         false,
         0,
         "73552b0c",
         null,
         null,
         false
      ],
      [
         "TO",
         [
            1308,
            "00fe051473552b0c597f0126597f0126597f0126597f0126597f0126597f0126597f0126597f0126597f0126597f0126597f0126597f0126597f0126597f0126 ..."
         ],
         false
      ],
      [
         "TF",
         [
            1300,
            "**************************************************************** ..."
         ],
         0,
         false,
         0,
         "78ad4a10",
         null,
         null,
         false
      ],
      [
         "TO",
         [
            1308,
            "00fe051478ad4a105287603a5287603a5287603a5287603a5287603a5287603a5287603a5287603a5287603a5287603a5287603a5287603a5287603a5287603a ..."
         ],
         false
      ],
      [
         "TF",
         [
            1300,
            "**************************************************************** ..."
         ],
         0,
         false,
         0,
         "a25fd2a9",
         null,
         null,
         false
      ],
      [
         "TO",
         [
            1308,
            "00fe0514a25fd2a98875f8838875f8838875f8838875f8838875f8838875f8838875f8838875f8838875f8838875f8838875f8838875f8838875f8838875f883 ..."
         ],
         false
      ],
      [
         "TF",
         [
            1300,
            "**************************************************************** ..."
         ],
         0,
         false,
         0,
         "b8a189aa",
         null,
         null,
         false
      ],
      [
         "TO",
         [
            1308,
            "00fe0514b8a189aa928ba380928ba380928ba380928ba380928ba380928ba380928ba380928ba380928ba380928ba380928ba380928ba380928ba380928ba380 ..."
         ],
         false
      ],
      [
         "TF",
         [
            1300,
            "**************************************************************** ..."
         ],
         0,
         false,
         0,
         "703b89c9",
         null,
         null,
         false
      ],
      [
         "TO",
         [
            1308,
            "00fe0514703b89c95a11a3e35a11a3e35a11a3e35a11a3e35a11a3e35a11a3e35a11a3e35a11a3e35a11a3e35a11a3e35a11a3e35a11a3e35a11a3e35a11a3e3 ..."
         ],
         false
      ],
      [
         "TF",
         [
            1300,
            "**************************************************************** ..."
         ],
         0,
         false,
         0,
         "8e1c8518",
         null,
         null,
         false
      ],
      [
         "TO",
         [
            1308,
            "00fe05148e1c8518a436af32a436af32a436af32a436af32a436af32a436af32a436af32a436af32a436af32a436af32a436af32a436af32a436af32a436af32 ..."
         ],
         false
      ],
      [
         "TF",
         [
            1300,
            "**************************************************************** ..."
         ],
         0,
         false,
         0,
         "f9737d97",
         null,
         null,
         false
      ],
      [
         "TO",
         [
            1308,
            "00fe0514f9737d97d35957bdd35957bdd35957bdd35957bdd35957bdd35957bdd35957bdd35957bdd35957bdd35957bdd35957bdd35957bdd35957bdd35957bd ..."
         ],
         false
      ],
      [
         "TF",
         [
            1300,
            "**************************************************************** ..."
         ],
         0,
         false,
         0,
         "5bdf457c",
         null,
         null,
         false
      ],
      [
         "TO",
         [
            1308,
            "00fe05145bdf457c71f56f5671f56f5671f56f5671f56f5671f56f5671f56f5671f56f5671f56f5671f56f5671f56f5671f56f5671f56f5671f56f5671f56f56 ..."
         ],
         false
      ],
      [
         "TF",
         [
            1300,
            "**************************************************************** ..."
         ],
         0,
         false,
         0,
         "7896e179",
         null,
         null,
         false
      ],
      [
         "TO",
         [
            1308,
            "00fe05147896e17952bccb5352bccb5352bccb5352bccb5352bccb5352bccb5352bccb5352bccb5352bccb5352bccb5352bccb5352bccb5352bccb5352bccb53 ..."
         ],
         false
      ],
      [
         "TF",
         [
            1300,
            "**************************************************************** ..."
         ],
         0,
         false,
         0,
         "fc0c695c",
         null,
         null,
         false
      ],
      [
         "TO",
         [
            1308,
            "00fe0514fc0c695cd6264376d6264376d6264376d6264376d6264376d6264376d6264376d6264376d6264376d6264376d6264376d6264376d6264376d6264376 ..."
         ],
         false
      ],
      [
         "TF",
         [
            1300,
            "**************************************************************** ..."
         ],
         0,
         false,
         0,
         "2471dc95",
         null,
         null,
         false
      ],
      [
         "TO",
         [
            1308,
            "00fe05142471dc950e5bf6bf0e5bf6bf0e5bf6bf0e5bf6bf0e5bf6bf0e5bf6bf0e5bf6bf0e5bf6bf0e5bf6bf0e5bf6bf0e5bf6bf0e5bf6bf0e5bf6bf0e5bf6bf ..."
         ],
         false
      ],
      [
         "TF",
         [
            1300,
            "**************************************************************** ..."
         ],
         0,
         false,
         0,
         "aa87c421",
         null,
         null,
         false
      ],
      [
         "TO",
         [
            1308,
            "00fe0514aa87c42180adee0b80adee0b80adee0b80adee0b80adee0b80adee0b80adee0b80adee0b80adee0b80adee0b80adee0b80adee0b80adee0b80adee0b ..."
         ],
         false
      ],
      [
         "TF",
         [
            1300,
            "**************************************************************** ..."
         ],
         0,
         false,
         0,
         "5fed5f1e",
         null,
         null,
         false
      ],
      [
         "TO",
         [
            1308,
            "00fe05145fed5f1e75c7753475c7753475c7753475c7753475c7753475c7753475c7753475c7753475c7753475c7753475c7753475c7753475c7753475c77534 ..."
         ],
         false
      ],
      [
         "TF",
         [
            1300,
            "**************************************************************** ..."
         ],
         0,
         false,
         0,
         "16a2b911",
         null,
         null,
         false
      ],
      [
         "TO",
         [
            1308,
            "00fe051416a2b9113c88933b3c88933b3c88933b3c88933b3c88933b3c88933b3c88933b3c88933b3c88933b3c88933b3c88933b3c88933b3c88933b3c88933b ..."
         ],
         false
      ],
      [
         "TF",
         [
            1300,
            "**************************************************************** ..."
         ],
         0,
         false,
         0,
         "2bacf1f6",
         null,
         null,
         false
      ],
      [
         "TO",
         [
            1308,
            "00fe05142bacf1f60186dbdc0186dbdc0186dbdc0186dbdc0186dbdc0186dbdc0186dbdc0186dbdc0186dbdc0186dbdc0186dbdc0186dbdc0186dbdc0186dbdc ..."
         ],
         false
      ],
      [
         "TF",
         [
            1300,
            "**************************************************************** ..."
         ],
         0,
         false,
         0,
         "e688cd90",
         null,
         null,
         false
      ],
      [
         "TO",
         [
            1308,
            "00fe0514e688cd90cca2e7bacca2e7bacca2e7bacca2e7bacca2e7bacca2e7bacca2e7bacca2e7bacca2e7bacca2e7bacca2e7bacca2e7bacca2e7bacca2e7ba ..."
         ],
         false
      ],
      [
         "TF",
         [
            1300,
            "**************************************************************** ..."
         ],
         0,
         false,
         0,
         "5ebeca41",
         null,
         null,
         false
      ],
      [
         "TO",
         [
            1308,
            "00fe05145ebeca417494e06b7494e06b7494e06b7494e06b7494e06b7494e06b7494e06b7494e06b7494e06b7494e06b7494e06b7494e06b7494e06b7494e06b ..."
         ],
         false
      ],
      [
         "TF",
         [
            1300,
            "**************************************************************** ..."
         ],
         0,
         false,
         0,
         "7d10a1f4",
         null,
         null,
         false
      ],
      [
         "TO",
         [
            1308,
            "00fe05147d10a1f4573a8bde573a8bde573a8bde573a8bde573a8bde573a8bde573a8bde573a8bde573a8bde573a8bde573a8bde573a8bde573a8bde573a8bde ..."
         ],
         false
      ],
      [
         "TF",
         [
            1300,
            "**************************************************************** ..."
         ],
         0,
         false,
         0,
         "826f245a",
         null,
         null,
         false
      ],
      [
         "TO",
         [
            1308,
            "00fe0514826f245aa8450e70a8450e70a8450e70a8450e70a8450e70a8450e70a8450e70a8450e70a8450e70a8450e70a8450e70a8450e70a8450e70a8450e70 ..."
         ],
         false
      ],
      [
         "TF",
         [
            1300,
            "**************************************************************** ..."
         ],
         0,
         false,
         0,
         "e1fb5c18",
         null,
         null,
         false
      ],
      [
         "TO",
         [
            1308,
            "00fe0514e1fb5c18cbd17632cbd17632cbd17632cbd17632cbd17632cbd17632cbd17632cbd17632cbd17632cbd17632cbd17632cbd17632cbd17632cbd17632 ..."
         ],
         false
      ],
      [
         "TF",
         [
            1300,
            "**************************************************************** ..."
         ],
         0,
         false,
         0,
         "616cfc11",
         null,
         null,
         false
      ],
      [
         "TO",
         [
            1308,
            "00fe0514616cfc114b46d63b4b46d63b4b46d63b4b46d63b4b46d63b4b46d63b4b46d63b4b46d63b4b46d63b4b46d63b4b46d63b4b46d63b4b46d63b4b46d63b ..."
         ],
         false
      ],
      [
         "TF",
         [
            1300,
            "**************************************************************** ..."
         ],
         0,
         false,
         0,
         "e8ed68f3",
         null,
         null,
         false
      ],
      [
         "TO",
         [
            1308,
            "00fe0514e8ed68f3c2c742d9c2c742d9c2c742d9c2c742d9c2c742d9c2c742d9c2c742d9c2c742d9c2c742d9c2c742d9c2c742d9c2c742d9c2c742d9c2c742d9 ..."
         ],
         false
      ],
      [
         "TF",
         [
            1300,
            "**************************************************************** ..."
         ],
         0,
         false,
         0,
         "acf76d1f",
         null,
         null,
         false
      ],
      [
         "TO",
         [
            1308,
            "00fe0514acf76d1f86dd473586dd473586dd473586dd473586dd473586dd473586dd473586dd473586dd473586dd473586dd473586dd473586dd473586dd4735 ..."
         ],
         false
      ],
      [
         "TF",
         [
            1300,
            "**************************************************************** ..."
         ],
         0,
         false,
         0,
         "4ed6f6cd",
         null,
         null,
         false
      ],
      [
         "TO",
         [
            1308,
            "00fe05144ed6f6cd64fcdce764fcdce764fcdce764fcdce764fcdce764fcdce764fcdce764fcdce764fcdce764fcdce764fcdce764fcdce764fcdce764fcdce7 ..."
         ],
         false
      ],
      [
         "TF",
         [
            1300,
            "**************************************************************** ..."
         ],
         0,
         false,
         0,
         "418e3f3f",
         null,
         null,
         false
      ],
      [
         "TO",
         [
            1308,
            "00fe0514418e3f3f6ba415156ba415156ba415156ba415156ba415156ba415156ba415156ba415156ba415156ba415156ba415156ba415156ba415156ba41515 ..."
         ],
         false
      ],
      [
         "TF",
         [
            1300,
            "**************************************************************** ..."
         ],
         0,
         false,
         0,
         "44d8a29e",
         null,
         null,
         false
      ],
      [
         "TO",
         [
            1308,
            "00fe051444d8a29e6ef288b46ef288b46ef288b46ef288b46ef288b46ef288b46ef288b46ef288b46ef288b46ef288b46ef288b46ef288b46ef288b46ef288b4 ..."
         ],
         false
      ],
      [
         "TF",
         [
            1300,
            "**************************************************************** ..."
         ],
         0,
         false,
         0,
         "12812a80",
         null,
         null,
         false
      ],
      [
         "TO",
         [
            1308,
            "00fe051412812a8038ab00aa38ab00aa38ab00aa38ab00aa38ab00aa38ab00aa38ab00aa38ab00aa38ab00aa38ab00aa38ab00aa38ab00aa38ab00aa38ab00aa ..."
         ],
         false
      ],
      [
         "TF",
         [
            1300,
            "**************************************************************** ..."
         ],
         0,
         false,
         0,
         "68ec847d",
         null,
         null,
         false
      ],
      [
         "TO",
         [
            1308,
            "00fe051468ec847d42c6ae5742c6ae5742c6ae5742c6ae5742c6ae5742c6ae5742c6ae5742c6ae5742c6ae5742c6ae5742c6ae5742c6ae5742c6ae5742c6ae57 ..."
         ],
         false
      ],
      [
         "TF",
         [
            1300,
            "**************************************************************** ..."
         ],
         0,
         false,
         0,
         "ba677cee",
         null,
         null,
         false
      ],
      [
         "TO",
         [
            1308,
            "00fe0514ba677cee904d56c4904d56c4904d56c4904d56c4904d56c4904d56c4904d56c4904d56c4904d56c4904d56c4904d56c4904d56c4904d56c4904d56c4 ..."
         ],
         false
      ],
      [
         "TF",
         [
            1300,
            "**************************************************************** ..."
         ],
         0,
         false,
         0,
         "fc87c756",
         null,
         null,
         false
      ],
      [
         "TO",
         [
            1308,
            "00fe0514fc87c756d6aded7cd6aded7cd6aded7cd6aded7cd6aded7cd6aded7cd6aded7cd6aded7cd6aded7cd6aded7cd6aded7cd6aded7cd6aded7cd6aded7c ..."
         ],
         false
      ],
      [
         "TF",
         [
            1300,
            "**************************************************************** ..."
         ],
         0,
         false,
         0,
         "866201de",
         null,
         null,
         false
      ],
      [
         "TO",
         [
            1308,
            "00fe0514866201deac482bf4ac482bf4ac482bf4ac482bf4ac482bf4ac482bf4ac482bf4ac482bf4ac482bf4ac482bf4ac482bf4ac482bf4ac482bf4ac482bf4 ..."
         ],
         false
      ],
      [
         "TF",
         [
            1300,
            "**************************************************************** ..."
         ],
         0,
         false,
         0,
         "f52993cd",
         null,
         null,
         false
      ],
      [
         "TO",
         [
            1308,
            "00fe0514f52993cddf03b9e7df03b9e7df03b9e7df03b9e7df03b9e7df03b9e7df03b9e7df03b9e7df03b9e7df03b9e7df03b9e7df03b9e7df03b9e7df03b9e7 ..."
         ],
         false
      ],
      [
         "TF",
         [
            1300,
            "**************************************************************** ..."
         ],
         0,
         false,
         0,
         "45730d17",
         null,
         null,
         false
      ],
      [
         "TO",
         [
            1308,
            "00fe051445730d176f59273d6f59273d6f59273d6f59273d6f59273d6f59273d6f59273d6f59273d6f59273d6f59273d6f59273d6f59273d6f59273d6f59273d ..."
         ],
         false
      ],
      [
         "TF",
         [
            1300,
            "**************************************************************** ..."
         ],
         0,
         false,
         0,
         "b166c8fb",
         null,
         null,
         false
      ],
      [
         "TO",
         [
            1308,
            "00fe0514b166c8fb9b4ce2d19b4ce2d19b4ce2d19b4ce2d19b4ce2d19b4ce2d19b4ce2d19b4ce2d19b4ce2d19b4ce2d19b4ce2d19b4ce2d19b4ce2d19b4ce2d1 ..."
         ],
         false
      ],
      [
         "TF",
         [
            1300,
            "**************************************************************** ..."
         ],
         0,
         false,
         0,
         "6a72bc06",
         null,
         null,
         false
      ],
      [
         "TO",
         [
            1308,
            "00fe05146a72bc064058962c4058962c4058962c4058962c4058962c4058962c4058962c4058962c4058962c4058962c4058962c4058962c4058962c4058962c ..."
         ],
         false
      ],
      [
         "TF",
         [
            536,
            "**************************************************************** ..."
         ],
         0,
         true,
         0,
         "b90f98fe",
         null,
         null,
         false
      ],
      [
         "TO",
         [
            544,
            "80fe0218b90f98fe9325b2d49325b2d49325b2d49325b2d49325b2d49325b2d49325b2d49325b2d49325b2d49325b2d49325b2d49325b2d49325b2d49325b2d4 ..."
         ],
         false
      ],
      [
         "KL",
         10
      ],
      [
         "RO",
         [
            40880,
            "817f00000000000100002a2a2a2a2a2a2a2a2a2a2a2a2a2a2a2a2a2a2a2a2a2a2a2a2a2a2a2a2a2a2a2a2a2a2a2a2a2a2a2a2a2a2a2a2a2a2a2a2a2a2a2a2a2a ..."
         ]
      ],
      [
         "RO",
         [
            24666,
            "2a2a2a2a2a2a2a2a2a2a2a2a2a2a2a2a2a2a2a2a2a2a2a2a2a2a2a2a2a2a2a2a2a2a2a2a2a2a2a2a2a2a2a2a2a2a2a2a2a2a2a2a2a2a2a2a2a2a2a2a2a2a2a2a ..."
         ]
      ],
      [
         "RF",
         [
            65536,
            "**************************************************************** ..."
         ],
         1,
         true,
         0,
         false,
         null
      ],
      [
         "TF",
         [
            2,
            "0x03e8"
         ],
         8,
         true,
         0,
         "faaafdbd",
         null,
         null,
         false
      ],
      [
         "TO",
         [
            8,
            "8882faaafdbdf942"
         ],
         false
      ],
      [
         "RO",
         [
            4,
            "880203e8"
         ]
      ],
      [
         "RF",
         [
            2,
            "0x03e8"
         ],
         8,
         true,
         0,
         false,
         null
      ]
   ]
}