{
   "agent": "Boost.Beast/189-Sync",
   "behavior": "OK",
   "behaviorClose": "OK",
   "case": 360,
   "closedByMe": true,
   "createStats": true,
   "createWirelog": true,
   "description": "Send 1000 compressed messages each of payload size 256, auto-fragment to 0 octets. Use default permessage-deflate offer.",
   "droppedByMe": false,
   "duration": 617,
   "expectation": "Receive echo'ed messages (with payload as sent). Timeout case after 120 secs.",
   "expected": {},
   "expectedClose": {
      "closeCode": [
         1000
      ],
      "closedByMe": true,
      "requireClean": true
   },
   "failedByMe": false,
   "httpRequest": "GET / HTTP/1.1\r\nUser-Agent: AutobahnTestSuite/0.8.0-0.10.9\r\nHost: 127.0.0.1:8080\r\nUpgrade: WebSocket\r\nConnection: Upgrade\r\nPragma: no-cache\r\nCache-Control: no-cache\r\nSec-WebSocket-Key: 76iRRPpNNOCtffWmDDINDw==\r\nSec-WebSocket-Extensions: permessage-deflate; client_no_context_takeover; client_max_window_bits\r\nSec-WebSocket-Version: 13\r\n\r\n",
   "httpResponse": "HTTP/1.1 101 Switching Protocols\r\nUpgrade: websocket\r\nConnection: upgrade\r\nSec-WebSocket-Accept: aCiQZ0w6pzWYLg+26UBi1/DtL+I=\r\nSec-WebSocket-Extensions: permessage-deflate; client_no_context_takeover\r\nServer: Boost.Beast/189-Sync\r\n\r\n",
   "id": "12.4.3",
   "isServer": false,
   "localCloseCode": 1000,
   "localCloseReason": null,
   "received": [],
   "remoteCloseCode": 1000,
   "remoteCloseReason": null,
   "reportCompressionRatio": true,
   "reportTime": true,
   "result": "Ok, received all echo'ed messages in time.",
   "resultClose": "Connection was properly closed",
   "rxFrameStats": {
      "1": 1000,
      "8": 1
   },
   "rxOctetStats": {
      "4": 1,
      "124": 1,
      "126": 1,
      "127": 2,
      "131": 1,
      "133": 7,
      "134": 9,
      "135": 5,
      "136": 4,
      "137": 14,
      "138": 26,
      "139": 25,
      "140": 33,
      "141": 40,
      "142": 37,
      "143": 29,
      "144": 17,
      "145": 9,
      "146": 7,
      "147": 6,
      "148": 6,
      "149": 5,
      "150": 5,
      "151": 7,
      "152": 9,
      "153": 7,
      "154": 9,
      "155": 9,
      "156": 15,
      "157": 7,
      "158": 6,
      "159": 13,
      "160": 12,
      "161": 16,
      "162": 10,
      "163": 10,
      "164": 11,
      "165": 15,
      "166": 22,
      "167": 18,
      "168": 11,
      "169": 13,
      "170": 16,
      "171": 16,
      "172": 15,
      "173": 28,
      "174": 24,
      "175": 18,
      "176": 22,
      "177": 29,
      "178": 27,
      "179": 34,
      "180": 36,
      "181": 31,
      "182": 34,
      "183": 21,
      "184": 20,
      "185": 17,
      "186": 16,
      "187": 15,
      "188": 13,
      "189": 13,
      "190": 10,
      "191": 11,
      "192": 8,
      "193": 1,
      "194": 4,
      "195": 3,
      "198": 1,
      "199": 2,
      "200": 1,
      "201": 2,
      "204": 1,
      "206": 1,
      "220": 1,
      "233": 1
   },
   "started": "2018-11-09T16:30:02.261Z",
   "trafficStats": {
      "incomingCompressionRatio": 0.6280236068852113,
      "incomingOctetsAppLevel": 256027,
      "incomingOctetsWebSocketLevel": 160791,
      "incomingOctetsWireLevel": 164783,
      "incomingWebSocketFrames": 1000,
      "incomingWebSocketMessages": 1000,
      "incomingWebSocketOverhead": 0.02482726023222693,
      "outgoingCompressionRatio": 0.623274107808942,
      "outgoingOctetsAppLevel": 256027,
      "outgoingOctetsWebSocketLevel": 159575,
      "outgoingOctetsWireLevel": 167565,
      "outgoingWebSocketFrames": 1000,
      "outgoingWebSocketMessages": 1000,
      "outgoingWebSocketOverhead": 0.05007049976500078,
      "preopenIncomingOctetsWireLevel": 233,
      "preopenOutgoingOctetsWireLevel": 338
   },
   "txFrameStats": {
      "1": 1000,
      "8": 1
   },
   "txOctetStats": {
      "8": 1,
      "128": 3,
      "129": 1,
      "130": 1,
      "134": 2,
      "135": 8,
      "136": 7,
      "137": 4,
      "138": 4,
      "139": 12,
      "140": 15,
      "141": 23,
      "142": 42,
      "143": 37,
      "144": 37,
      "145": 39,
      "146": 16,
      "147": 9,
      "148": 7,
      "149": 3,
      "150": 8,
      "151": 5,
      "152": 4,
      "153": 7,
      "154": 7,
      "155": 7,
      "156": 8,
      "157": 12,
      "158": 12,
      "159": 7,
      "160": 10,
      "161": 9,
      "162": 15,
      "163": 7,
      "164": 16,
      "165": 8,
      "166": 12,
      "167": 8,
      "168": 15,
      "169": 19,
      "170": 21,
      "171": 12,
      "172": 13,
      "173": 14,
      "174": 12,
      "175": 19,
      "176": 24,
      "177": 25,
      "178": 19,
      "179": 23,
      "180": 24,
      "181": 33,
      "182": 46,
      "183": 29,
      "184": 21,
      "185": 21,
      "186": 29,
      "187": 19,
      "188": 19,
      "189": 10,
      "190": 24,
      "191": 11,
      "192": 11,
      "193": 13,
      "194": 10,
      "195": 10,
      "196": 5,
      "197": 1,
      "198": 4,
      "199": 3,
      "202": 2,
      "203": 2,
      "205": 2,
      "208": 1,
      "209": 1,
      "224": 1,
      "338": 1
   },
   "wasClean": true,
   "wasCloseHandshakeTimeout": false,
   "wasNotCleanReason": null,
   "wasOpenHandshakeTimeout": false,
   "wasServerConnectionDropTimeout": false,
   "wirelog": [
      [
         "TO",
         [
            338,
            "474554202f20485454502f312e310d0a557365722d4167656e743a204175746f6261686e5465737453756974652f302e382e302d302e31302e390d0a486f7374 ..."
         ],
         false
      ],
      [
         "RO",
         [
            233,
            "485454502f312e312031303120537769746368696e672050726f746f636f6c730d0a557067726164653a20776562736f636b65740d0a436f6e6e656374696f6e ..."
         ]
      ],
      [
         "WLM",
         false
      ],
      [
         "TI",
         120
      ],
      [
         "WLM",
         true
      ],
      [
         "TF",
         [
            2,
            "0x03e8"
         ],
         8,
         true,
         0,
         "e4358652",
         null,
         null,
         false
      ],
      [
         "TO",
         [
            8,
            "8882e4358652e7dd"
         ],
         false
      ],
      [
         "RO",
         [
            4,
            "880203e8"
         ]
      ],
      [
         "RF",
         [
            2,
            "0x03e8"
         ],
         8,
         true,
         0,
         false,
         null
      ]
   ]
}